{
    "modules": [
        {
            "module": "modulo_1",
            "playlist": [
                {
                    "id": "0",
                    "title_video": "Classificação das raízes quanto a ocorrência, forma e função",
                    "subtitle_video": "",
                    "thumb_video": "https://stensineme.blob.core.windows.net/hmlgrepoh/00212sa/02969/json/img_1.png",
                    "link_video": "https://play.yduqs.videolib.live/index.html?token=f276597161444de581cb62f13d6c56f5",
                    "paragraph": "",
                    "time": "2min39s",
                    "border_bottom": "true"
                },
                {
                    "id": "1",
                    "title_video": "Formação e projeção de raízes secundárias",
                    "subtitle_video": "",
                    "thumb_video": "https://stensineme.blob.core.windows.net/hmlgrepoh/00212sa/02969/json/img_2.png",
                    "link_video": "https://play.yduqs.videolib.live/index.html?token=64bdfeecbce9433db1b2f9409f4df217",
                    "paragraph": "",
                    "time": "1min48s",
                    "border_bottom": "true"
                }
            ]
        },
        {
            "module": "modulo_2",
            "playlist": [
                {
                    "id": "0",
                    "title_video": "Classificação quanto a ocorrência, forma e função de caules",
                    "subtitle_video": "",
                    "thumb_video": "https://stensineme.blob.core.windows.net/hmlgrepoh/00212sa/02969/json/img_1.png",
                    "link_video": "https://play.yduqs.videolib.live/index.html?token=8f237e43be1b44c3a2cd51db7a7b8fd0",
                    "paragraph": "",
                    "time": "3min03s",
                    "border_bottom": "true"
                },
                {
                    "id": "1",
                    "title_video": "Crescimento e espessamento secundário de caules",
                    "subtitle_video": "",
                    "thumb_video": "https://stensineme.blob.core.windows.net/hmlgrepoh/00212sa/02969/json/img_2.png",
                    "link_video": "https://play.yduqs.videolib.live/index.html?token=3395e04214a14bcc8394b78ea4bda43a",
                    "paragraph": "",
                    "time": "2min16s",
                    "border_bottom": "true"
                }
            ]
        },
        {
            "module": "modulo_3",
            "playlist": [
                {
                    "id": "0",
                    "title_video": "Adaptações na epiderme da folha",
                    "subtitle_video": "",
                    "thumb_video": "https://stensineme.blob.core.windows.net/hmlgrepoh/00212sa/02969/json/img_1.png",
                    "link_video": "https://play.yduqs.videolib.live/index.html?token=3de7d3175d4b412d9cf0a28cdc6a543b",
                    "paragraph": "",
                    "time": "1min55s",
                    "border_bottom": "true"
                },
                {
                    "id": "1",
                    "title_video": "Classificação e adaptações do mesofilo",
                    "subtitle_video": "",
                    "thumb_video": "https://stensineme.blob.core.windows.net/hmlgrepoh/00212sa/02969/json/img_2.png",
                    "link_video": "https://play.yduqs.videolib.live/index.html?token=898e1a23357240858498937dce6f59e5",
                    "paragraph": "",
                    "time": "1min55s",
                    "border_bottom": "true"
                }
            ]
        },
        {
            "module": "modulo_4",
            "playlist": [
                {
                    "id": "0",
                    "title_video": "Classificação quanto a organização das inflorescências",
                    "subtitle_video": "",
                    "thumb_video": "https://stensineme.blob.core.windows.net/hmlgrepoh/00212sa/02969/json/img_1.png",
                    "link_video": "https://play.yduqs.videolib.live/index.html?token=838cfe41fd7f4350ac832ccf81f769aa",
                    "paragraph": "",
                    "time": "3min08s",
                    "border_bottom": "true"
                },
                {
                    "id": "1",
                    "title_video": "Classificação quanto a forma dos frutos",
                    "subtitle_video": "",
                    "thumb_video": "https://stensineme.blob.core.windows.net/hmlgrepoh/00212sa/02969/json/img_2.png",
                    "link_video": "https://play.yduqs.videolib.live/index.html?token=0d83c2d98ebb4d10b5850e1cad7d3a21",
                    "paragraph": "",
                    "time": "3min01s",
                    "border_bottom": "true"
                }
            ]
        }
    ]
}